camex/__init__.py
camex/cam_ex.py
camex/.vscode/settings.json
camex/__pycache__/__init__.cpython-37.pyc
camex/addons/__pycache__/test.cpython-38.pyc
camex/addons/cvx/Huber_regression/references.txt
camex/addons/cvx/L1_trend_filtering/__init__.py
camex/addons/cvx/L1_trend_filtering/execute.py
camex/addons/cvx/L1_trend_filtering/get_stock_data.py
camex/addons/cvx/L1_trend_filtering/references.txt
camex/addons/cvx/L1_trend_filtering/saved.py
camex/addons/cvx/L1_trend_filtering/data/bc.csv
camex/addons/cvx/L1_trend_filtering/data/input_data.csv
camex/addons/cvx/L1_trend_filtering/html/help.html
camex/addons/cvx/L1_trend_filtering/html/markdown.md
camex/addons/cvx/Portfolio_optimization/__init__.py
camex/addons/cvx/Portfolio_optimization/create_data.py
camex/addons/cvx/Portfolio_optimization/execute.py
camex/addons/cvx/Portfolio_optimization/references.txt
camex/addons/cvx/Portfolio_optimization/saved.py
camex/addons/cvx/Portfolio_optimization/data/mu_data.csv
camex/addons/cvx/Portfolio_optimization/data/sigma_data.csv
camex/addons/cvx/Portfolio_optimization/html/help.html
camex/addons/cvx/Portfolio_optimization/html/markdown.md
camex/addons/cvx/Portfolio_optimization_2/__init__.py
camex/addons/cvx/Portfolio_optimization_2/create_data.py
camex/addons/cvx/Portfolio_optimization_2/execute.py
camex/addons/cvx/Portfolio_optimization_2/references.txt
camex/addons/cvx/Portfolio_optimization_2/saved.py
camex/addons/cvx/Portfolio_optimization_2/data/mu_data.csv
camex/addons/cvx/Portfolio_optimization_2/data/sigma_data.csv
camex/addons/cvx/Portfolio_optimization_2/html/help.html
camex/addons/cvx/Portfolio_optimization_2/html/markdown.md
camex/addons/cvx/Portfolio_optimization_2/html/images/trade_off_curves.png
camex/addons/cvx/Quantile_regression/references.txt
camex/addons/cvx/__pycache__/test.cpython-38.pyc
camex/app_data/__init__.py
camex/app_data/addon_data.py
camex/app_data/ui_info.py
camex/app_data/__pycache__/__init__.cpython-37.pyc
camex-0.0.1a3.dist-info/METADATA
camex-0.0.1a3.dist-info/WHEEL
camex-0.0.1a3.dist-info/entry_points.txt
camex-0.0.1a3.dist-info/license.txt
camex-0.0.1a3.dist-info/top_level.txt
camex-0.0.1a3.dist-info/RECORD
