Metadata-Version: 2.1
Name: camex
Version: 0.0.1a3
Summary: Computational Applied Mathematics EXamples
Home-page: https://andreikeino.github.io/camex/introduction.html
Author: Andrei Keino
Author-email: andreikeino@gmail.com
License: LICENSE.txt
Platform: UNKNOWN
Requires-Python: >=3.7
Requires-Dist: PyQtWebEngine
Requires-Dist: qtconsole
Requires-Dist: matplotlib
Requires-Dist: cvxpy
Requires-Dist: cvxopt
Requires-Dist: pandas
Requires-Dist: pandas-datareader
